{
  "filename": "September 24.pdf",
  "date": "September 26, 2024",
  "attendees": [
    "Arelis Perez, Chair",
    "Robert Catlin, Vice Chair",
    "James McFadden, Commissioner",
    "Michelle Johnson, Executive Director",
    "Amanda Goode, Property Manager",
    "Cheryl Gleason, Finance Manager",
    "Charlotte Davis, ROSS Coordinator",
    "Elizabeth Norman, Commissioner",
    "Jennifer Burris, Accountant",
    "Ms. Patterson, Resident",
    "Ms. Keeler, Commissioner",
    "Theresa Keeler, Commissioner"
  ],
  "residents_comments": [
    "Mr. Patterson discussed the Cruz Development, and the new city clerk."
  ],
  "executive_directors_report": [
    "Revised budget LHA 2024-04/operating budget for FY 2025",
    "Repositioning",
    "RFP for the elevator contract awarded to TK Elevators",
    "RFP for various building projects",
    "7 Vacancies",
    "Vigal Contractors working on the stacks",
    "Elevator update (scheduled inspection)",
    "Bill bond update"
  ],
  "decisions": [
    "Agenda approved",
    "September 26 Cleanup Day (shredding paper 10/12/24) and (bulk trash 10/12/24-10/19/24), and Day (10/26/24) approved",
    "Free flu and covid vaccinations at Costco discussed",
    "ARPA funds, Earmark funds (Federal program), discussed",
    "Budget for 2025 approved",
    "Invoices over $4,000 approved",
    "Motion for resident guide approved"
  ],
  "raw_text": "..."
}